Metadata-Version: 2.4
Name: llama-index-readers-wordpress
Version: 0.4.1
Summary: llama-index readers wordpress integration
Author-email: Your Name <you@example.com>
Maintainer: bbornsztein
License-Expression: MIT
License-File: LICENSE
Keywords: blog,wordpress
Requires-Python: <4.0,>=3.9
Requires-Dist: llama-index-core<0.15,>=0.13.0
